{
  "name": "xml-to-json",
  "title": "XML to JSON Converter",
  "description": "Transform XML documents into JSON format with pretty formatting",
  "content": "<h3 class=\"heading-node\">Overview</h3><p class=\"text-node\">This application converts XML documents into JSON format. Built using <a class=\"link\" href=\"https://github.com/martinblech/xmltodict\" target=\"_blank\">xmltodict</a>, it preserves the structure and hierarchy of your XML data while transforming it into a more web-friendly JSON format.</p><h3 class=\"heading-node\">Features</h3><ul class=\"list-node\"><li class=\"list-item-node\">Convert XML to JSON format</li><li class=\"list-item-node\">Pretty-printed JSON output for readability</li><li class=\"list-item-node\">Preserves XML structure and attributes</li><li class=\"list-item-node\">UTF-8 encoding support</li></ul><h3 class=\"heading-node\">Parameters</h3><ul class=\"list-node\"><li class=\"list-item-node\"><strong>XML File</strong>: Upload your XML file from stash</li><li class=\"list-item-node\"><strong>Output Directory</strong>: Select or create a stash folder for output</li></ul><h3 class=\"heading-node\">Output</h3><p class=\"text-node\">The application generates a JSON file with the same base name as the input XML file in the specified output directory.</p><h3 class=\"heading-node\">Use Cases</h3><ul class=\"list-node\"><li class=\"list-item-node\">Converting configuration files to JSON</li><li class=\"list-item-node\">Transforming API responses between formats</li><li class=\"list-item-node\">Preparing XML data for web applications</li><li class=\"list-item-node\">Data migration and format standardization</li></ul>",
  "command": "REPO_DIR=\"prod_apps_$$PPID\"; rm -rf \"$REPO_DIR\" 2>/dev/null || true; git clone https://github.com/CamberCloud-Inc/prod_apps.git \"$REPO_DIR\" && python \"$REPO_DIR/python/xml_to_json.py\" \"${xmlPath}\" -o \"${outputDir}\"",
  "engineType": "MPI",
  "jobConfig": [
    {
      "type": "Select",
      "label": "System Size",
      "name": "system_size",
      "hidden": true,
      "description": "Select the configuration for the job",
      "options": [
        {
          "label": "Extra Extra Small CPU",
          "value": "xxsmall_cpu",
          "mapValue": {
            "nodeSize": "XXSMALL",
            "numNodes": 1,
            "withGpu": false
          }
        }
      ],
      "defaultValue": "xxsmall_cpu"
    }
  ],
  "spec": [
    {
      "type": "Stash File",
      "name": "xmlPath",
      "label": "XML File",
      "description": "Upload the XML file you want to convert to JSON",
      "defaultValue": ""
    },
    {
      "type": "Stash File",
      "name": "outputDir",
      "label": "Output Directory",
      "description": "Select or create a stash folder where the JSON file will be saved",
      "defaultValue": "./"
    }
  ]
}